[
  {
    "name": "טחינה אמיתית",
    "code": "P_7290106577282",
    "categories": "",
    "price": "15.5",
    "weight_g": null,
    "source_category": "A162406_hummus_tahini",
    "query": "A162406_hummus_tahini",
    "suggested_decision": "REVIEW",
    "decision_reason": "needs_manual_check",
    "approved_for_scrape": "NO"
  },
  {
    "name": "חציל על האש בטחינה",
    "code": "P_7290106577480",
    "categories": "",
    "price": "15.5",
    "weight_g": null,
    "source_category": "A162406_hummus_tahini",
    "query": "A162406_hummus_tahini",
    "suggested_decision": "REVIEW",
    "decision_reason": "needs_manual_check",
    "approved_for_scrape": "NO"
  },
  {
    "name": "טחינה לבנה",
    "code": "P_7290105366047",
    "categories": "",
    "price": "16.5",
    "weight_g": null,
    "source_category": "A162406_hummus_tahini",
    "query": "A162406_hummus_tahini",
    "suggested_decision": "REVIEW",
    "decision_reason": "needs_manual_check",
    "approved_for_scrape": "NO"
  },
  {
    "name": "חומוס מסעדה צבר",
    "code": "P_7290106576537",
    "categories": "",
    "price": "11.9",
    "weight_g": null,
    "source_category": "A162406_hummus_tahini",
    "query": "A162406_hummus_tahini",
    "suggested_decision": "YES",
    "decision_reason": "positive_type:חומוס",
    "approved_for_scrape": "NO"
  },
  {
    "name": "חומוס",
    "code": "P_7296073725589",
    "categories": "",
    "price": "10.9",
    "weight_g": null,
    "source_category": "A162406_hummus_tahini",
    "query": "A162406_hummus_tahini",
    "suggested_decision": "YES",
    "decision_reason": "positive_type:חומוס",
    "approved_for_scrape": "NO"
  },
  {
    "name": "חומוס",
    "code": "P_8645935",
    "categories": "",
    "price": "11.9",
    "weight_g": null,
    "source_category": "A162406_hummus_tahini",
    "query": "A162406_hummus_tahini",
    "suggested_decision": "YES",
    "decision_reason": "positive_type:חומוס",
    "approved_for_scrape": "NO"
  },
  {
    "name": "חומוס",
    "code": "P_2987963",
    "categories": "",
    "price": "15.3",
    "weight_g": null,
    "source_category": "A162406_hummus_tahini",
    "query": "A162406_hummus_tahini",
    "suggested_decision": "YES",
    "decision_reason": "positive_type:חומוס",
    "approved_for_scrape": "NO"
  },
  {
    "name": "חומוס מסעדה",
    "code": "P_3727667",
    "categories": "",
    "price": "16.9",
    "weight_g": null,
    "source_category": "A162406_hummus_tahini",
    "query": "A162406_hummus_tahini",
    "suggested_decision": "YES",
    "decision_reason": "positive_type:חומוס",
    "approved_for_scrape": "NO"
  },
  {
    "name": "חומוס גלילי",
    "code": "P_7290110557478",
    "categories": "",
    "price": "14.5",
    "weight_g": null,
    "source_category": "A162406_hummus_tahini",
    "query": "A162406_hummus_tahini",
    "suggested_decision": "YES",
    "decision_reason": "positive_type:חומוס",
    "approved_for_scrape": "NO"
  },
  {
    "name": "חומוס",
    "code": "P_7290105964564",
    "categories": "",
    "price": "10.0",
    "weight_g": null,
    "source_category": "A162406_hummus_tahini",
    "query": "A162406_hummus_tahini",
    "suggested_decision": "YES",
    "decision_reason": "positive_type:חומוס",
    "approved_for_scrape": "NO"
  },
  {
    "name": "חומוס אסלי",
    "code": "P_7296073725565",
    "categories": "",
    "price": "10.9",
    "weight_g": null,
    "source_category": "A162406_hummus_tahini",
    "query": "A162406_hummus_tahini",
    "suggested_decision": "YES",
    "decision_reason": "positive_type:חומוס",
    "approved_for_scrape": "NO"
  },
  {
    "name": "סלט חומוס",
    "code": "P_6666307",
    "categories": "",
    "price": "14.9",
    "weight_g": null,
    "source_category": "A162406_hummus_tahini",
    "query": "A162406_hummus_tahini",
    "suggested_decision": "YES",
    "decision_reason": "positive_type:חומוס",
    "approved_for_scrape": "NO"
  },
  {
    "name": "חומוס אבו גוש",
    "code": "P_7296073725381",
    "categories": "",
    "price": "12.9",
    "weight_g": null,
    "source_category": "A162406_hummus_tahini",
    "query": "A162406_hummus_tahini",
    "suggested_decision": "YES",
    "decision_reason": "positive_type:חומוס",
    "approved_for_scrape": "NO"
  },
  {
    "name": "חומוס מסעדות",
    "code": "P_7296073725404",
    "categories": "",
    "price": "12.9",
    "weight_g": null,
    "source_category": "A162406_hummus_tahini",
    "query": "A162406_hummus_tahini",
    "suggested_decision": "YES",
    "decision_reason": "positive_type:חומוס",
    "approved_for_scrape": "NO"
  },
  {
    "name": "חומוס מסבחה",
    "code": "P_7296073725398",
    "categories": "",
    "price": "12.9",
    "weight_g": null,
    "source_category": "A162406_hummus_tahini",
    "query": "A162406_hummus_tahini",
    "suggested_decision": "YES",
    "decision_reason": "positive_type:חומוס",
    "approved_for_scrape": "NO"
  },
  {
    "name": "חומוס מסעדה",
    "code": "P_7290106576513",
    "categories": "",
    "price": "12.5",
    "weight_g": null,
    "source_category": "A162406_hummus_tahini",
    "query": "A162406_hummus_tahini",
    "suggested_decision": "YES",
    "decision_reason": "positive_type:חומוס",
    "approved_for_scrape": "NO"
  },
  {
    "name": "חומוס עם זעתר",
    "code": "P_7290104061424",
    "categories": "",
    "price": "11.9",
    "weight_g": null,
    "source_category": "A162406_hummus_tahini",
    "query": "A162406_hummus_tahini",
    "suggested_decision": "YES",
    "decision_reason": "positive_type:חומוס",
    "approved_for_scrape": "NO"
  },
  {
    "name": "חומוס עם טחינה אחלה",
    "code": "P_7290104061417",
    "categories": "",
    "price": "11.9",
    "weight_g": null,
    "source_category": "A162406_hummus_tahini",
    "query": "A162406_hummus_tahini",
    "suggested_decision": "YES",
    "decision_reason": "positive_type:חומוס",
    "approved_for_scrape": "NO"
  },
  {
    "name": "חומוס עם צנובר אחלה",
    "code": "P_7290104061431",
    "categories": "",
    "price": "11.9",
    "weight_g": null,
    "source_category": "A162406_hummus_tahini",
    "query": "A162406_hummus_tahini",
    "suggested_decision": "YES",
    "decision_reason": "positive_type:חומוס",
    "approved_for_scrape": "NO"
  },
  {
    "name": "חומוס עם חריף אחלה",
    "code": "P_7290104061448",
    "categories": "",
    "price": "11.9",
    "weight_g": null,
    "source_category": "A162406_hummus_tahini",
    "query": "A162406_hummus_tahini",
    "suggested_decision": "YES",
    "decision_reason": "positive_type:חומוס",
    "approved_for_scrape": "NO"
  },
  {
    "name": "חומוס לבנוני צבר",
    "code": "P_7290106573598",
    "categories": "",
    "price": "13.9",
    "weight_g": null,
    "source_category": "A162406_hummus_tahini",
    "query": "A162406_hummus_tahini",
    "suggested_decision": "YES",
    "decision_reason": "positive_type:חומוס",
    "approved_for_scrape": "NO"
  },
  {
    "name": "חומוס עם טחינה צבר",
    "code": "P_7290106573628",
    "categories": "",
    "price": "13.9",
    "weight_g": null,
    "source_category": "A162406_hummus_tahini",
    "query": "A162406_hummus_tahini",
    "suggested_decision": "YES",
    "decision_reason": "positive_type:חומוס",
    "approved_for_scrape": "NO"
  },
  {
    "name": "חומוס צנובר צבר",
    "code": "P_7290106573642",
    "categories": "",
    "price": "13.9",
    "weight_g": null,
    "source_category": "A162406_hummus_tahini",
    "query": "A162406_hummus_tahini",
    "suggested_decision": "YES",
    "decision_reason": "positive_type:חומוס",
    "approved_for_scrape": "NO"
  },
  {
    "name": "חומוס אבו גוש+צנובר+חריף",
    "code": "P_7290106573819",
    "categories": "",
    "price": "13.9",
    "weight_g": null,
    "source_category": "A162406_hummus_tahini",
    "query": "A162406_hummus_tahini",
    "suggested_decision": "YES",
    "decision_reason": "positive_type:חומוס",
    "approved_for_scrape": "NO"
  },
  {
    "name": "חומוס עם זעתר",
    "code": "P_7290115202434",
    "categories": "",
    "price": "13.9",
    "weight_g": null,
    "source_category": "A162406_hummus_tahini",
    "query": "A162406_hummus_tahini",
    "suggested_decision": "YES",
    "decision_reason": "positive_type:חומוס",
    "approved_for_scrape": "NO"
  },
  {
    "name": "חומוס עם חריף",
    "code": "P_7290115202687",
    "categories": "",
    "price": "13.9",
    "weight_g": null,
    "source_category": "A162406_hummus_tahini",
    "query": "A162406_hummus_tahini",
    "suggested_decision": "YES",
    "decision_reason": "positive_type:חומוס",
    "approved_for_scrape": "NO"
  },
  {
    "name": "מלך החומוס אבו מרוואן",
    "code": "P_467320",
    "categories": "",
    "price": "16.5",
    "weight_g": null,
    "source_category": "A162406_hummus_tahini",
    "query": "A162406_hummus_tahini",
    "suggested_decision": "YES",
    "decision_reason": "positive_type:חומוס",
    "approved_for_scrape": "NO"
  },
  {
    "name": "מלך החומוס סמיר הגדול",
    "code": "P_467153",
    "categories": "",
    "price": "16.5",
    "weight_g": null,
    "source_category": "A162406_hummus_tahini",
    "query": "A162406_hummus_tahini",
    "suggested_decision": "YES",
    "decision_reason": "positive_type:חומוס",
    "approved_for_scrape": "NO"
  },
  {
    "name": "חומוס גרגרים בתטבילה",
    "code": "P_7290112968685",
    "categories": "",
    "price": "16.5",
    "weight_g": null,
    "source_category": "A162406_hummus_tahini",
    "query": "A162406_hummus_tahini",
    "suggested_decision": "YES",
    "decision_reason": "positive_type:חומוס",
    "approved_for_scrape": "NO"
  },
  {
    "name": "חומוס גלילי",
    "code": "P_7290110579319",
    "categories": "",
    "price": "12.5",
    "weight_g": null,
    "source_category": "A162406_hummus_tahini",
    "query": "A162406_hummus_tahini",
    "suggested_decision": "YES",
    "decision_reason": "positive_type:חומוס",
    "approved_for_scrape": "NO"
  },
  {
    "name": "חומוס ישראלי",
    "code": "P_7290119387434",
    "categories": "",
    "price": "12.5",
    "weight_g": null,
    "source_category": "A162406_hummus_tahini",
    "query": "A162406_hummus_tahini",
    "suggested_decision": "YES",
    "decision_reason": "positive_type:חומוס",
    "approved_for_scrape": "NO"
  },
  {
    "name": "חומוס מועשר 40% עם חריף",
    "code": "P_7290119373710",
    "categories": "",
    "price": "11.3",
    "weight_g": null,
    "source_category": "A162406_hummus_tahini",
    "query": "A162406_hummus_tahini",
    "suggested_decision": "YES",
    "decision_reason": "positive_type:חומוס",
    "approved_for_scrape": "NO"
  },
  {
    "name": "סלט חציל פיקנטי",
    "code": "P_3989096",
    "categories": "",
    "price": "16.9",
    "weight_g": null,
    "source_category": "A162403_eggplant",
    "query": "A162403_eggplant",
    "suggested_decision": "REVIEW",
    "decision_reason": "needs_manual_check",
    "approved_for_scrape": "NO"
  },
  {
    "name": "סלט חציל בטעם כבד",
    "code": "P_7290105366023",
    "categories": "",
    "price": "16.5",
    "weight_g": null,
    "source_category": "A162403_eggplant",
    "query": "A162403_eggplant",
    "suggested_decision": "REVIEW",
    "decision_reason": "needs_manual_check",
    "approved_for_scrape": "NO"
  },
  {
    "name": "סלט שום כתוש",
    "code": "P_2862017",
    "categories": "",
    "price": "16.5",
    "weight_g": null,
    "source_category": "A162403_eggplant",
    "query": "A162403_eggplant",
    "suggested_decision": "REVIEW",
    "decision_reason": "needs_manual_check",
    "approved_for_scrape": "NO"
  },
  {
    "name": "ממרח עגבניות מיובשות",
    "code": "P_7290015858113",
    "categories": "",
    "price": "17.9",
    "weight_g": null,
    "source_category": "A162403_eggplant",
    "query": "A162403_eggplant",
    "suggested_decision": "REVIEW",
    "decision_reason": "possible_target",
    "approved_for_scrape": "NO"
  },
  {
    "name": "ממרח פלפלים קלויים",
    "code": "P_7290015858175",
    "categories": "",
    "price": "17.9",
    "weight_g": null,
    "source_category": "A162403_eggplant",
    "query": "A162403_eggplant",
    "suggested_decision": "YES",
    "decision_reason": "positive_type:ממרח פלפל",
    "approved_for_scrape": "NO"
  },
  {
    "name": "ממרח פלפלים קלויים",
    "code": "P_7296073451969",
    "categories": "",
    "price": "14.5",
    "weight_g": null,
    "source_category": "A162403_eggplant",
    "query": "A162403_eggplant",
    "suggested_decision": "YES",
    "decision_reason": "positive_type:ממרח פלפל",
    "approved_for_scrape": "NO"
  },
  {
    "name": "ממרח עגבניות מיובשות",
    "code": "P_7296073451976",
    "categories": "",
    "price": "14.5",
    "weight_g": null,
    "source_category": "A162403_eggplant",
    "query": "A162403_eggplant",
    "suggested_decision": "REVIEW",
    "decision_reason": "possible_target",
    "approved_for_scrape": "NO"
  },
  {
    "name": "ממרח צ'ימיצ'ורי",
    "code": "P_7296073451990",
    "categories": "",
    "price": "14.5",
    "weight_g": null,
    "source_category": "A162403_eggplant",
    "query": "A162403_eggplant",
    "suggested_decision": "REVIEW",
    "decision_reason": "possible_target",
    "approved_for_scrape": "NO"
  },
  {
    "name": "סלט מטבוחה",
    "code": "P_7290010931330",
    "categories": "",
    "price": "15.9",
    "weight_g": null,
    "source_category": "A162408_schug_matbucha",
    "query": "A162408_schug_matbucha",
    "suggested_decision": "YES",
    "decision_reason": "positive_type:מטבוחה",
    "approved_for_scrape": "NO"
  },
  {
    "name": "סלט טורקי",
    "code": "P_7290106520905",
    "categories": "",
    "price": "16.5",
    "weight_g": null,
    "source_category": "A162408_schug_matbucha",
    "query": "A162408_schug_matbucha",
    "suggested_decision": "YES",
    "decision_reason": "positive_type:סלט טורקי",
    "approved_for_scrape": "NO"
  },
  {
    "name": "מטבוחה חריפה",
    "code": "P_7290111563492",
    "categories": "",
    "price": "15.5",
    "weight_g": null,
    "source_category": "A162408_schug_matbucha",
    "query": "A162408_schug_matbucha",
    "suggested_decision": "YES",
    "decision_reason": "positive_type:מטבוחה",
    "approved_for_scrape": "NO"
  },
  {
    "name": "סלט מטבוחה מרוקאית",
    "code": "P_7290011800642",
    "categories": "",
    "price": "18.5",
    "weight_g": null,
    "source_category": "A162408_schug_matbucha",
    "query": "A162408_schug_matbucha",
    "suggested_decision": "YES",
    "decision_reason": "positive_type:מטבוחה",
    "approved_for_scrape": "NO"
  },
  {
    "name": "סלט מטבוחה יום יום",
    "code": "P_8644112",
    "categories": "",
    "price": "5.0",
    "weight_g": null,
    "source_category": "A162408_schug_matbucha",
    "query": "A162408_schug_matbucha",
    "suggested_decision": "YES",
    "decision_reason": "positive_type:מטבוחה",
    "approved_for_scrape": "NO"
  },
  {
    "name": "חומוס מוקפא",
    "code": "P_7296073705505",
    "categories": "[A160501, A510102, A51, A16, categories, A, A5101, A1605]",
    "price": "17.9",
    "weight_g": null,
    "source_category": "search",
    "query": "חומוס",
    "tier": "mainstream",
    "suggested_decision": "YES",
    "decision_reason": "positive_type:חומוס",
    "approved_for_scrape": "NO"
  },
  {
    "name": "סלט חומוס+מסבחה",
    "code": "P_7296073725367",
    "categories": "[A16, A1624, A162407, categories, A]",
    "price": "10.9",
    "weight_g": null,
    "source_category": "search",
    "query": "חומוס",
    "tier": "mainstream",
    "suggested_decision": "YES",
    "decision_reason": "positive_type:חומוס",
    "approved_for_scrape": "NO"
  },
  {
    "name": "חומוס שלם יכין",
    "code": "P_208428",
    "categories": "[A221707, A2217, A22, categories, A]",
    "price": "10.0",
    "weight_g": null,
    "source_category": "search",
    "query": "חומוס",
    "tier": "mainstream",
    "suggested_decision": "YES",
    "decision_reason": "positive_type:חומוס",
    "approved_for_scrape": "NO"
  },
  {
    "name": "חומוס יום יום",
    "code": "P_5174551",
    "categories": "[A24, A16, A2406, A1624, A162407, A162406, categories, A]",
    "price": "5.0",
    "weight_g": null,
    "source_category": "search",
    "query": "חומוס",
    "tier": "mainstream",
    "suggested_decision": "YES",
    "decision_reason": "positive_type:חומוס",
    "approved_for_scrape": "NO"
  },
  {
    "name": "חומוס",
    "code": "P_3643714",
    "categories": "[A2211, A22, categories, A, A221104]",
    "price": "9.9",
    "weight_g": null,
    "source_category": "search",
    "query": "חומוס",
    "tier": "mainstream",
    "suggested_decision": "YES",
    "decision_reason": "positive_type:חומוס",
    "approved_for_scrape": "NO"
  },
  {
    "name": "חומוס",
    "code": "P_1990261",
    "categories": "[A2211, A22, categories, A, A221104]",
    "price": "16.5",
    "weight_g": null,
    "source_category": "search",
    "query": "חומוס",
    "tier": "mainstream",
    "suggested_decision": "YES",
    "decision_reason": "positive_type:חומוס",
    "approved_for_scrape": "NO"
  },
  {
    "name": "סלט חומוס עם טחינה",
    "code": "P_7296073725374",
    "categories": "[A16, A1624, A162407, categories, A]",
    "price": "10.9",
    "weight_g": null,
    "source_category": "search",
    "query": "חומוס",
    "tier": "mainstream",
    "suggested_decision": "YES",
    "decision_reason": "positive_type:חומוס",
    "approved_for_scrape": "NO"
  },
  {
    "name": "חומוס",
    "code": "P_7296073733324",
    "categories": "[A2211, A22, categories, A, A221104]",
    "price": "9.9",
    "weight_g": null,
    "source_category": "search",
    "query": "חומוס",
    "tier": "mainstream",
    "suggested_decision": "YES",
    "decision_reason": "positive_type:חומוס",
    "approved_for_scrape": "NO"
  },
  {
    "name": "חומוס",
    "code": "P_7296073733317",
    "categories": "[A2211, A22, categories, A, A221104]",
    "price": "16.5",
    "weight_g": null,
    "source_category": "search",
    "query": "חומוס",
    "tier": "mainstream",
    "suggested_decision": "YES",
    "decision_reason": "positive_type:חומוס",
    "approved_for_scrape": "NO"
  },
  {
    "name": "חומוס ענק",
    "code": "P_3643820",
    "categories": "[A2211, A22, categories, A, A221104]",
    "price": "10.9",
    "weight_g": null,
    "source_category": "search",
    "query": "חומוס",
    "tier": "mainstream",
    "suggested_decision": "YES",
    "decision_reason": "positive_type:חומוס",
    "approved_for_scrape": "NO"
  },
  {
    "name": "חומוס גדול שופרסל",
    "code": "P_7296073006015",
    "categories": "[A2211, A22, categories, A, A221104]",
    "price": "13.9",
    "weight_g": null,
    "source_category": "search",
    "query": "חומוס",
    "tier": "mainstream",
    "suggested_decision": "YES",
    "decision_reason": "positive_type:חומוס",
    "approved_for_scrape": "NO"
  },
  {
    "name": "חומוס גדול גרגרים שופרסל",
    "code": "P_7296073005872",
    "categories": "[A2211, A22, categories, A, A221104]",
    "price": "8.9",
    "weight_g": null,
    "source_category": "search",
    "query": "חומוס",
    "tier": "mainstream",
    "suggested_decision": "YES",
    "decision_reason": "positive_type:חומוס",
    "approved_for_scrape": "NO"
  },
  {
    "name": "חומוס ענק",
    "code": "P_7296073733348",
    "categories": "[A2211, A22, categories, A, A221104]",
    "price": "19.9",
    "weight_g": null,
    "source_category": "search",
    "query": "חומוס",
    "tier": "mainstream",
    "suggested_decision": "YES",
    "decision_reason": "positive_type:חומוס",
    "approved_for_scrape": "NO"
  },
  {
    "name": "חומוס ענק",
    "code": "P_7296073733331",
    "categories": "[A2211, A22, categories, A, A221104]",
    "price": "10.9",
    "weight_g": null,
    "source_category": "search",
    "query": "חומוס",
    "tier": "mainstream",
    "suggested_decision": "YES",
    "decision_reason": "positive_type:חומוס",
    "approved_for_scrape": "NO"
  },
  {
    "name": "חומוס לבן ענק שופרסל",
    "code": "P_7296073005889",
    "categories": "[A2211, A22, categories, A, A221104]",
    "price": "9.9",
    "weight_g": null,
    "source_category": "search",
    "query": "חומוס",
    "tier": "mainstream",
    "suggested_decision": "YES",
    "decision_reason": "positive_type:חומוס",
    "approved_for_scrape": "NO"
  },
  {
    "name": "חטיפוני גזר",
    "code": "P_7290016584004",
    "categories": "[A24, A04, A0410, categories, A041001, A, A2409]",
    "price": "7.9",
    "weight_g": null,
    "source_category": "search",
    "query": "ממרח חומוס",
    "tier": "mainstream",
    "suggested_decision": "REVIEW",
    "decision_reason": "needs_manual_check",
    "approved_for_scrape": "NO"
  },
  {
    "name": "ממרח אבוקדו",
    "code": "P_7290119379934",
    "categories": "[A16, A1624, A162407, categories, A]",
    "price": "18.5",
    "weight_g": null,
    "source_category": "search",
    "query": "ממרח חומוס",
    "tier": "mainstream",
    "suggested_decision": "REVIEW",
    "decision_reason": "possible_target",
    "approved_for_scrape": "NO"
  },
  {
    "name": "ממרח גוואקמולי",
    "code": "P_7290115677959",
    "categories": "[A16, A1624, A162407, categories, A]",
    "price": "18.5",
    "weight_g": null,
    "source_category": "search",
    "query": "ממרח חומוס",
    "tier": "mainstream",
    "suggested_decision": "REVIEW",
    "decision_reason": "possible_target",
    "approved_for_scrape": "NO"
  },
  {
    "name": "קוקוס לשתיה +קשית",
    "code": "P_8719325243659",
    "categories": "[A04, A0410, categories, A041001, A]",
    "price": "24.9",
    "weight_g": null,
    "source_category": "search",
    "query": "ממרח חומוס",
    "tier": "mainstream",
    "suggested_decision": "REVIEW",
    "decision_reason": "needs_manual_check",
    "approved_for_scrape": "NO"
  },
  {
    "name": "ממרח חמאה עם מלח",
    "code": "P_5740900403215",
    "categories": "[A011908, A0119, categories, A, A01]",
    "price": "18.3",
    "weight_g": null,
    "source_category": "search",
    "query": "ממרח חומוס",
    "tier": "mainstream",
    "suggested_decision": "REVIEW",
    "decision_reason": "possible_target",
    "approved_for_scrape": "NO"
  },
  {
    "name": "ממרח חמאה ללא מלח",
    "code": "P_5740900403239",
    "categories": "[A011908, A0119, categories, A, A01]",
    "price": "18.3",
    "weight_g": null,
    "source_category": "search",
    "query": "ממרח חומוס",
    "tier": "mainstream",
    "suggested_decision": "REVIEW",
    "decision_reason": "possible_target",
    "approved_for_scrape": "NO"
  },
  {
    "name": "ממרח חמאה עם מלח",
    "code": "P_5740900403253",
    "categories": "[A011908, A0119, categories, A, A01]",
    "price": "31.9",
    "weight_g": null,
    "source_category": "search",
    "query": "ממרח חומוס",
    "tier": "mainstream",
    "suggested_decision": "REVIEW",
    "decision_reason": "possible_target",
    "approved_for_scrape": "NO"
  },
  {
    "name": "גרגרי חומוס",
    "code": "P_7296073732679",
    "categories": "[A221707, A2217, A22, categories, A]",
    "price": "9.9",
    "weight_g": null,
    "source_category": "search",
    "query": "ממרח חומוס",
    "tier": "mainstream",
    "suggested_decision": "YES",
    "decision_reason": "positive_type:חומוס",
    "approved_for_scrape": "NO"
  },
  {
    "name": "ממרח חמאה מופחת שומן+מלח",
    "code": "P_5740900403222",
    "categories": "[A011908, A0119, categories, A, A01]",
    "price": "18.3",
    "weight_g": null,
    "source_category": "search",
    "query": "ממרח חומוס",
    "tier": "mainstream",
    "suggested_decision": "REVIEW",
    "decision_reason": "possible_target",
    "approved_for_scrape": "NO"
  },
  {
    "name": "ממרח חמאה מופחת שומן",
    "code": "P_5740900403260",
    "categories": "[A011908, A0119, categories, A, A01]",
    "price": "18.3",
    "weight_g": null,
    "source_category": "search",
    "query": "ממרח חומוס",
    "tier": "mainstream",
    "suggested_decision": "REVIEW",
    "decision_reason": "possible_target",
    "approved_for_scrape": "NO"
  },
  {
    "name": "ממרח חמאה ללא מלח",
    "code": "P_5740900403246",
    "categories": "[A011908, A0119, categories, A, A01]",
    "price": "31.9",
    "weight_g": null,
    "source_category": "search",
    "query": "ממרח חומוס",
    "tier": "mainstream",
    "suggested_decision": "REVIEW",
    "decision_reason": "possible_target",
    "approved_for_scrape": "NO"
  },
  {
    "name": "ממרח זעתר",
    "code": "P_7296073429821",
    "categories": "[A22, A222008, categories, A2220, A]",
    "price": "14.9",
    "weight_g": null,
    "source_category": "search",
    "query": "ממרח חומוס",
    "tier": "mainstream",
    "suggested_decision": "REVIEW",
    "decision_reason": "possible_target",
    "approved_for_scrape": "NO"
  },
  {
    "name": "ממרח זיתי קלמטה",
    "code": "P_7296073723400",
    "categories": "[A22, A222008, categories, A2220, A]",
    "price": "14.9",
    "weight_g": null,
    "source_category": "search",
    "query": "ממרח חומוס",
    "tier": "mainstream",
    "suggested_decision": "REVIEW",
    "decision_reason": "possible_target",
    "approved_for_scrape": "NO"
  },
  {
    "name": "ממרח עגבניות מיובשות",
    "code": "P_7296073723417",
    "categories": "[A22, A222008, categories, A2220, A]",
    "price": "14.9",
    "weight_g": null,
    "source_category": "search",
    "query": "ממרח חומוס",
    "tier": "mainstream",
    "suggested_decision": "REVIEW",
    "decision_reason": "possible_target",
    "approved_for_scrape": "NO"
  },
  {
    "name": "גרגירי חומוס טטרה פק",
    "code": "P_7296073497189",
    "categories": "[A510102, A51, A221707, A2217, A22, categories, A5101, A]",
    "price": "6.9",
    "weight_g": null,
    "source_category": "search",
    "query": "ממרח חומוס",
    "tier": "mainstream",
    "suggested_decision": "YES",
    "decision_reason": "positive_type:חומוס",
    "approved_for_scrape": "NO"
  },
  {
    "name": "מארז שום קלוף",
    "code": "P_7296073612926",
    "categories": "[A04, A0410, categories, A041001, A]",
    "price": "12.9",
    "weight_g": null,
    "source_category": "search",
    "query": "חומוס שום",
    "tier": "mainstream",
    "suggested_decision": "REVIEW",
    "decision_reason": "needs_manual_check",
    "approved_for_scrape": "NO"
  },
  {
    "name": "מארז שום יבש",
    "code": "P_7296073751045",
    "categories": "[A04, A0410, categories, A041001, A]",
    "price": "6.9",
    "weight_g": null,
    "source_category": "search",
    "query": "חומוס שום",
    "tier": "mainstream",
    "suggested_decision": "REVIEW",
    "decision_reason": "needs_manual_check",
    "approved_for_scrape": "NO"
  },
  {
    "name": "מארז שום פנינה",
    "code": "P_7290018394083",
    "categories": "[A04, A0410, categories, A041001, A]",
    "price": "13.9",
    "weight_g": null,
    "source_category": "search",
    "query": "חומוס שום",
    "tier": "mainstream",
    "suggested_decision": "REVIEW",
    "decision_reason": "needs_manual_check",
    "approved_for_scrape": "NO"
  },
  {
    "name": "מארז שום קלוף",
    "code": "P_7296073755401",
    "categories": "[A04, A0410, categories, A041001, A]",
    "price": "20.9",
    "weight_g": null,
    "source_category": "search",
    "query": "חומוס שום",
    "tier": "mainstream",
    "suggested_decision": "REVIEW",
    "decision_reason": "needs_manual_check",
    "approved_for_scrape": "NO"
  },
  {
    "name": "מארז שום קלוף",
    "code": "P_7296073755395",
    "categories": "[A04, A0410, categories, A041001, A]",
    "price": "10.9",
    "weight_g": null,
    "source_category": "search",
    "query": "חומוס שום",
    "tier": "mainstream",
    "suggested_decision": "REVIEW",
    "decision_reason": "needs_manual_check",
    "approved_for_scrape": "NO"
  },
  {
    "name": "שיני שום מקולף אורגני",
    "code": "P_6902023070524",
    "categories": "[A04, categories, F01, A281704, F010202, A0411, F, A0410, A2817, A28, A041001, A, F0102, A041102]",
    "price": "14.9",
    "weight_g": null,
    "source_category": "search",
    "query": "חומוס שום",
    "tier": "mainstream",
    "suggested_decision": "REVIEW",
    "decision_reason": "needs_manual_check",
    "approved_for_scrape": "NO"
  },
  {
    "name": "שום יבש ברשת אורגני",
    "code": "P_7290016270952",
    "categories": "[A04, categories, F01, A281704, F010202, A0411, F, A0410, A2817, A28, A041001, A, F0102, A041102]",
    "price": "20.9",
    "weight_g": null,
    "source_category": "search",
    "query": "חומוס שום",
    "tier": "mainstream",
    "suggested_decision": "REVIEW",
    "decision_reason": "needs_manual_check",
    "approved_for_scrape": "NO"
  },
  {
    "name": "תיבוליות שום ופטרוזיליה",
    "code": "P_3804320",
    "categories": "[A22, categories, A220807, A, A2208]",
    "price": "11.5",
    "weight_g": null,
    "source_category": "search",
    "query": "חומוס שום",
    "tier": "mainstream",
    "suggested_decision": "REVIEW",
    "decision_reason": "needs_manual_check",
    "approved_for_scrape": "NO"
  },
  {
    "name": "איולי שום",
    "code": "P_7296073726272",
    "categories": "[A22, A222008, categories, A2220, A]",
    "price": "14.9",
    "weight_g": null,
    "source_category": "search",
    "query": "חומוס שום",
    "tier": "mainstream",
    "suggested_decision": "REVIEW",
    "decision_reason": "needs_manual_check",
    "approved_for_scrape": "NO"
  },
  {
    "name": "פלפל חריף",
    "code": "P_619",
    "categories": "[A24, A04, A0410, categories, A041001, A, A2420]",
    "price": "12.9",
    "weight_g": null,
    "source_category": "search",
    "query": "חומוס חריף",
    "tier": "mainstream",
    "suggested_decision": "REVIEW",
    "decision_reason": "needs_manual_check",
    "approved_for_scrape": "NO"
  },
  {
    "name": "פלפל חריף ארוז",
    "code": "P_7296073440567",
    "categories": "[A04, A0410, categories, A041001, A]",
    "price": "12.9",
    "weight_g": null,
    "source_category": "search",
    "query": "חומוס חריף",
    "tier": "mainstream",
    "suggested_decision": "REVIEW",
    "decision_reason": "needs_manual_check",
    "approved_for_scrape": "NO"
  },
  {
    "name": "פלפל חריף חלפיניו",
    "code": "P_7290016809046",
    "categories": "[A04, A0410, categories, A041001, A]",
    "price": "13.9",
    "weight_g": null,
    "source_category": "search",
    "query": "חומוס חריף",
    "tier": "mainstream",
    "suggested_decision": "REVIEW",
    "decision_reason": "needs_manual_check",
    "approved_for_scrape": "NO"
  },
  {
    "name": "מארז פלפל צ'ילי חריף",
    "code": "P_7290016809039",
    "categories": "[A04, A0410, categories, A041001, A]",
    "price": "7.9",
    "weight_g": null,
    "source_category": "search",
    "query": "חומוס חריף",
    "tier": "mainstream",
    "suggested_decision": "REVIEW",
    "decision_reason": "needs_manual_check",
    "approved_for_scrape": "NO"
  },
  {
    "name": "פלפל חריף הבנרו",
    "code": "P_7290016809053",
    "categories": "[A04, A0410, categories, A041001, A]",
    "price": "13.9",
    "weight_g": null,
    "source_category": "search",
    "query": "חומוס חריף",
    "tier": "mainstream",
    "suggested_decision": "REVIEW",
    "decision_reason": "needs_manual_check",
    "approved_for_scrape": "NO"
  },
  {
    "name": "פלפל צילי-אריזה מוגדלת",
    "code": "P_7290018443545",
    "categories": "[A04, A0410, categories, A041001, A]",
    "price": "10.9",
    "weight_g": null,
    "source_category": "search",
    "query": "חומוס חריף",
    "tier": "mainstream",
    "suggested_decision": "REVIEW",
    "decision_reason": "needs_manual_check",
    "approved_for_scrape": "NO"
  },
  {
    "name": "פלפל צילי",
    "code": "P_7290016334388",
    "categories": "[A04, A0410, categories, A041001, A]",
    "price": "7.9",
    "weight_g": null,
    "source_category": "search",
    "query": "חומוס חריף",
    "tier": "mainstream",
    "suggested_decision": "REVIEW",
    "decision_reason": "needs_manual_check",
    "approved_for_scrape": "NO"
  },
  {
    "name": "מארז פלפל צילי",
    "code": "P_7296073751069",
    "categories": "[A04, A0410, categories, A041001, A]",
    "price": "7.9",
    "weight_g": null,
    "source_category": "search",
    "query": "חומוס חריף",
    "tier": "mainstream",
    "suggested_decision": "REVIEW",
    "decision_reason": "needs_manual_check",
    "approved_for_scrape": "NO"
  },
  {
    "name": "מארז מיקס חריף אש",
    "code": "P_7290016809077",
    "categories": "[A04, A0410, categories, A041001, A]",
    "price": "13.9",
    "weight_g": null,
    "source_category": "search",
    "query": "חומוס חריף",
    "tier": "mainstream",
    "suggested_decision": "REVIEW",
    "decision_reason": "needs_manual_check",
    "approved_for_scrape": "NO"
  },
  {
    "name": "טחינה בלאדי פלפלים חריף",
    "code": "P_7290112966728",
    "categories": "[A16, A1624, A162407, A162406, categories, A]",
    "price": "17.5",
    "weight_g": null,
    "source_category": "search",
    "query": "חומוס חריף",
    "tier": "mainstream",
    "suggested_decision": "REVIEW",
    "decision_reason": "needs_manual_check",
    "approved_for_scrape": "NO"
  },
  {
    "name": "חומוס עם מלא מטבוחה חריף",
    "code": "P_7290119374892",
    "categories": "[A16, A1624, A162407, categories, A]",
    "price": "12.9",
    "weight_g": null,
    "source_category": "search",
    "query": "חומוס חריף",
    "tier": "mainstream",
    "suggested_decision": "YES",
    "decision_reason": "positive_type:חומוס",
    "approved_for_scrape": "NO"
  },
  {
    "name": "מטבוחה חריפה אש",
    "code": "P_7290107958639",
    "categories": "[A24, A16, A1624, A162407, categories, A, A2420]",
    "price": "16.5",
    "weight_g": null,
    "source_category": "search",
    "query": "חומוס חריף",
    "tier": "mainstream",
    "suggested_decision": "YES",
    "decision_reason": "positive_type:מטבוחה",
    "approved_for_scrape": "NO"
  },
  {
    "name": "מנה חמה נודלס ויאטנמי",
    "code": "P_7290112969538",
    "categories": "[A22, categories, A, A220810, A2208]",
    "price": "7.9",
    "weight_g": null,
    "source_category": "search",
    "query": "חומוס חריף",
    "tier": "mainstream",
    "suggested_decision": "REVIEW",
    "decision_reason": "needs_manual_check",
    "approved_for_scrape": "NO"
  },
  {
    "name": "מנה חמה נודלס קוריאני",
    "code": "P_7290112969989",
    "categories": "[A22, categories, A, A220810, A2208]",
    "price": "7.9",
    "weight_g": null,
    "source_category": "search",
    "query": "חומוס חריף",
    "tier": "mainstream",
    "suggested_decision": "REVIEW",
    "decision_reason": "needs_manual_check",
    "approved_for_scrape": "NO"
  },
  {
    "name": "שמן זית כתית מעולה",
    "code": "P_7290120871090",
    "categories": "[A2226, A222601, A22, categories, A]",
    "price": "39.9",
    "weight_g": null,
    "source_category": "search",
    "query": "חומוס דל שומן",
    "tier": "mainstream",
    "suggested_decision": "REVIEW",
    "decision_reason": "needs_manual_check",
    "approved_for_scrape": "NO"
  },
  {
    "name": "חלב 3% שומן מהדרין",
    "code": "P_7290116936307",
    "categories": "[A010701, categories, A, A0107, A01]",
    "price": "14.7",
    "weight_g": null,
    "source_category": "search",
    "query": "חומוס דל שומן",
    "tier": "mainstream",
    "suggested_decision": "REVIEW",
    "decision_reason": "needs_manual_check",
    "approved_for_scrape": "NO"
  },
  {
    "name": "שמן זית כתית מעולה",
    "code": "P_7296073703785",
    "categories": "[A2226, A222601, A22, categories, A500701, A]",
    "price": "39.9",
    "weight_g": null,
    "source_category": "search",
    "query": "חומוס דל שומן",
    "tier": "mainstream",
    "suggested_decision": "REVIEW",
    "decision_reason": "needs_manual_check",
    "approved_for_scrape": "NO"
  },
  {
    "name": "שמן זית כתית מעולה",
    "code": "P_7296073693284",
    "categories": "[D, A2226, A222601, A22, categories, A500701, A, A500901]",
    "price": "39.9",
    "weight_g": null,
    "source_category": "search",
    "query": "חומוס דל שומן",
    "tier": "mainstream",
    "suggested_decision": "REVIEW",
    "decision_reason": "needs_manual_check",
    "approved_for_scrape": "NO"
  },
  {
    "name": "חלב בקרטון 3% שומן",
    "code": "P_4131074",
    "categories": "[A1501, A010701, A150101, categories, A, A15, A0107, A01]",
    "price": "7.35",
    "weight_g": null,
    "source_category": "search",
    "query": "חומוס דל שומן",
    "tier": "mainstream",
    "suggested_decision": "REVIEW",
    "decision_reason": "needs_manual_check",
    "approved_for_scrape": "NO"
  },
  {
    "name": "גרגירי חומוס אורגניים",
    "code": "P_7296073224402",
    "categories": "[A2211, F, F0303, A280225, A22, A2802, categories, F030301, A28, F03, A, A221104]",
    "price": "14.9",
    "weight_g": null,
    "source_category": "search",
    "query": "חומוס אורגני",
    "tier": "specialty",
    "suggested_decision": "YES",
    "decision_reason": "positive_type:חומוס",
    "approved_for_scrape": "NO"
  },
  {
    "name": "גרגירי חומוס אורגנית",
    "code": "P_8014515335382",
    "categories": "[F, A280213, F0304, A2802, F030402, categories, A28, F03, A]",
    "price": "9.9",
    "weight_g": null,
    "source_category": "search",
    "query": "חומוס אורגני",
    "tier": "specialty",
    "suggested_decision": "YES",
    "decision_reason": "positive_type:חומוס",
    "approved_for_scrape": "NO"
  },
  {
    "name": "קארי חומוס אורגני+אורז",
    "code": "P_7290018265246",
    "categories": "",
    "price": "24.5",
    "weight_g": null,
    "source_category": "search",
    "query": "חומוס אורגני",
    "tier": "specialty",
    "suggested_decision": "YES",
    "decision_reason": "positive_type:חומוס",
    "approved_for_scrape": "NO"
  },
  {
    "name": "חסה אורגני",
    "code": "P_7290013090157",
    "categories": "[A04, F01, categories, A281704, A281702, A0411, F010201, F, A0410, A2817, A041001, A28, F0102, A, A041102]",
    "price": "9.9",
    "weight_g": null,
    "source_category": "search",
    "query": "חומוס אורגני",
    "tier": "specialty",
    "suggested_decision": "REVIEW",
    "decision_reason": "needs_manual_check",
    "approved_for_scrape": "NO"
  },
  {
    "name": "פטרוזיליה אורגני",
    "code": "P_7290013090515",
    "categories": "[A04, F01, categories, A281704, A281702, A0411, F010201, F, A0410, A2817, A041001, A28, F0102, A, A041102]",
    "price": "9.9",
    "weight_g": null,
    "source_category": "search",
    "query": "חומוס אורגני",
    "tier": "specialty",
    "suggested_decision": "REVIEW",
    "decision_reason": "needs_manual_check",
    "approved_for_scrape": "NO"
  },
  {
    "name": "כוסברה אורגני",
    "code": "P_7290013090492",
    "categories": "[A04, F01, categories, A281704, A281702, A0411, F010201, F, A0410, A2817, A041001, A28, F0102, A, A041102]",
    "price": "9.9",
    "weight_g": null,
    "source_category": "search",
    "query": "חומוס אורגני",
    "tier": "specialty",
    "suggested_decision": "REVIEW",
    "decision_reason": "needs_manual_check",
    "approved_for_scrape": "NO"
  },
  {
    "name": "לוף אורגני",
    "code": "P_7290013090386",
    "categories": "[A04, F01, categories, A281704, A281702, A0411, F010201, F, A0410, A2817, A041001, A28, F0102, A, A041102]",
    "price": "16.9",
    "weight_g": null,
    "source_category": "search",
    "query": "חומוס אורגני",
    "tier": "specialty",
    "suggested_decision": "REVIEW",
    "decision_reason": "needs_manual_check",
    "approved_for_scrape": "NO"
  },
  {
    "name": "קייל אורגני",
    "code": "P_7290013090409",
    "categories": "[A04, F01, categories, A281704, A281702, A0411, F010201, F, A0410, A2817, A041001, A28, F0102, A, A041102]",
    "price": "14.9",
    "weight_g": null,
    "source_category": "search",
    "query": "חומוס אורגני",
    "tier": "specialty",
    "suggested_decision": "REVIEW",
    "decision_reason": "needs_manual_check",
    "approved_for_scrape": "NO"
  },
  {
    "name": "נענע אורגני",
    "code": "P_7290013090508",
    "categories": "[A04, F01, categories, A281704, A281702, A0411, F010201, F, A0410, A2817, A041001, A28, F0102, A, A041102]",
    "price": "9.9",
    "weight_g": null,
    "source_category": "search",
    "query": "חומוס אורגני",
    "tier": "specialty",
    "suggested_decision": "REVIEW",
    "decision_reason": "needs_manual_check",
    "approved_for_scrape": "NO"
  },
  {
    "name": "בוקצ'וי אורגני",
    "code": "P_7290013090430",
    "categories": "[A04, F01, categories, A281704, A281702, A0411, F010201, F, A0410, A2817, A041001, A28, F0102, A, A041102]",
    "price": "15.9",
    "weight_g": null,
    "source_category": "search",
    "query": "חומוס אורגני",
    "tier": "specialty",
    "suggested_decision": "REVIEW",
    "decision_reason": "needs_manual_check",
    "approved_for_scrape": "NO"
  },
  {
    "name": "נענע אורגני",
    "code": "P_7296073424451",
    "categories": "[A04, F01, categories, A281704, A281702, A0411, F010201, F, A0410, A2817, A041001, A28, F0102, A, A041102]",
    "price": "9.9",
    "weight_g": null,
    "source_category": "search",
    "query": "חומוס אורגני",
    "tier": "specialty",
    "suggested_decision": "REVIEW",
    "decision_reason": "needs_manual_check",
    "approved_for_scrape": "NO"
  },
  {
    "name": "אגס אורגני",
    "code": "P_7290018758373",
    "categories": "[A041101, A04, F010204, categories, F01, A041002, A0411, F, A281701, A0410, A2817, A28, A, F0102]",
    "price": "17.9",
    "weight_g": null,
    "source_category": "search",
    "query": "חומוס אורגני",
    "tier": "specialty",
    "suggested_decision": "REVIEW",
    "decision_reason": "needs_manual_check",
    "approved_for_scrape": "NO"
  },
  {
    "name": "מלון אורגני ארוז",
    "code": "P_9136975",
    "categories": "[A041101, A04, F010204, categories, F01, A041002, A0411, F, A281701, A0410, A2817, A28, A, F0102]",
    "price": "14.9",
    "weight_g": null,
    "source_category": "search",
    "query": "חומוס אורגני",
    "tier": "specialty",
    "suggested_decision": "REVIEW",
    "decision_reason": "needs_manual_check",
    "approved_for_scrape": "NO"
  },
  {
    "name": "אפרסק אורגני",
    "code": "P_7290018758502",
    "categories": "[A041101, A04, F010204, categories, F01, A041002, A0411, F, A281701, A0410, A2817, A28, A, F0102]",
    "price": "22.9",
    "weight_g": null,
    "source_category": "search",
    "query": "חומוס אורגני",
    "tier": "specialty",
    "suggested_decision": "REVIEW",
    "decision_reason": "needs_manual_check",
    "approved_for_scrape": "NO"
  },
  {
    "name": "תירס אורגני מארז",
    "code": "P_970738",
    "categories": "[A04, categories, F01, A281704, F010202, A0411, F, A0410, A2817, A041001, A28, A, F0102, A041102]",
    "price": "18.9",
    "weight_g": null,
    "source_category": "search",
    "query": "חומוס אורגני",
    "tier": "specialty",
    "suggested_decision": "REVIEW",
    "decision_reason": "needs_manual_check",
    "approved_for_scrape": "NO"
  },
  {
    "name": "חסה לבבות אורגנית",
    "code": "P_7290013090171",
    "categories": "[A04, F01, categories, A281704, A281702, A0411, F010201, F, A0410, A2817, A041001, A28, F0102, A, A041102]",
    "price": "16.9",
    "weight_g": null,
    "source_category": "search",
    "query": "חומוס אורגני",
    "tier": "specialty",
    "suggested_decision": "REVIEW",
    "decision_reason": "needs_manual_check",
    "approved_for_scrape": "NO"
  },
  {
    "name": "חסה לאליק אורגנית",
    "code": "P_7290018758045",
    "categories": "[A04, F01, categories, A281704, A281702, A0411, F010201, F, A0410, A2817, A28, A041001, F0102, A, A041102]",
    "price": "16.9",
    "weight_g": null,
    "source_category": "search",
    "query": "חומוס אורגני",
    "tier": "specialty",
    "suggested_decision": "REVIEW",
    "decision_reason": "needs_manual_check",
    "approved_for_scrape": "NO"
  },
  {
    "name": "סלרי עלים אורגני",
    "code": "P_7290013090225",
    "categories": "[A04, F01, categories, A281704, A281702, A0411, F010201, F, A0410, A2817, A041001, A28, F0102, A, A041102]",
    "price": "10.9",
    "weight_g": null,
    "source_category": "search",
    "query": "חומוס אורגני",
    "tier": "specialty",
    "suggested_decision": "REVIEW",
    "decision_reason": "needs_manual_check",
    "approved_for_scrape": "NO"
  },
  {
    "name": "בצל ירוק אורגני",
    "code": "P_7290013090379",
    "categories": "[A04, F01, categories, A281704, A281702, A0411, F010201, F, A0410, A2817, A041001, A28, F0102, A, A041102]",
    "price": "9.9",
    "weight_g": null,
    "source_category": "search",
    "query": "חומוס אורגני",
    "tier": "specialty",
    "suggested_decision": "REVIEW",
    "decision_reason": "needs_manual_check",
    "approved_for_scrape": "NO"
  },
  {
    "name": "יוגורט ביו 3% שומן דנונה",
    "code": "P_408316",
    "categories": "[A0113, categories, A011304, A, A012203, A01]",
    "price": "4.5",
    "weight_g": null,
    "source_category": "search",
    "query": "חומוס ביו",
    "tier": "specialty",
    "suggested_decision": "REVIEW",
    "decision_reason": "needs_manual_check",
    "approved_for_scrape": "NO"
  },
  {
    "name": "יוגורט ביו 1.7% דנונה",
    "code": "P_4584528",
    "categories": "[A0113, categories, A011304, A, A01]",
    "price": "4.5",
    "weight_g": null,
    "source_category": "search",
    "query": "חומוס ביו",
    "tier": "specialty",
    "suggested_decision": "REVIEW",
    "decision_reason": "needs_manual_check",
    "approved_for_scrape": "NO"
  },
  {
    "name": "דנונה ביו מולטי",
    "code": "P_7290110558284",
    "categories": "[A0113, categories, A011304, A, A01]",
    "price": "5.1",
    "weight_g": null,
    "source_category": "search",
    "query": "חומוס ביו",
    "tier": "specialty",
    "suggested_decision": "REVIEW",
    "decision_reason": "needs_manual_check",
    "approved_for_scrape": "NO"
  },
  {
    "name": "יוגורט דנונה ביו 3%",
    "code": "P_5839078",
    "categories": "[A0113, categories, A011304, A, A01]",
    "price": "19.9",
    "weight_g": null,
    "source_category": "search",
    "query": "חומוס ביו",
    "tier": "specialty",
    "suggested_decision": "REVIEW",
    "decision_reason": "needs_manual_check",
    "approved_for_scrape": "NO"
  },
  {
    "name": "חומוס עשיר ב40% טחינה",
    "code": "P_7290110564360",
    "categories": "[A16, A1624, A162406, categories, A]",
    "price": "14.9",
    "weight_g": null,
    "source_category": "search",
    "query": "חומוס קל",
    "tier": "specialty",
    "suggested_decision": "YES",
    "decision_reason": "positive_type:חומוס",
    "approved_for_scrape": "NO"
  },
  {
    "name": "צנובר",
    "code": "P_267616",
    "categories": "[A04, A040201, A220513, A2205, A22, categories, A0402, A]",
    "price": "29.9",
    "weight_g": null,
    "source_category": "search",
    "query": "חומוס עם צנוברים",
    "tier": "specialty",
    "suggested_decision": "REVIEW",
    "decision_reason": "needs_manual_check",
    "approved_for_scrape": "NO"
  },
  {
    "name": "צנובר",
    "code": "P_7296073705840",
    "categories": "[A04, A040201, A220513, A2205, A22, categories, A0402, A]",
    "price": "24.9",
    "weight_g": null,
    "source_category": "search",
    "query": "חומוס עם צנוברים",
    "tier": "specialty",
    "suggested_decision": "REVIEW",
    "decision_reason": "needs_manual_check",
    "approved_for_scrape": "NO"
  },
  {
    "name": "צנוברים",
    "code": "P_976556",
    "categories": "[A04, categories, A040210, A0402, A]",
    "price": "199.0",
    "weight_g": null,
    "source_category": "search",
    "query": "חומוס עם צנוברים",
    "tier": "specialty",
    "suggested_decision": "REVIEW",
    "decision_reason": "needs_manual_check",
    "approved_for_scrape": "NO"
  },
  {
    "name": "מטבוחה פיקנטית",
    "code": "P_7296073725633",
    "categories": "[A16, A1624, A162407, categories, A]",
    "price": "12.9",
    "weight_g": null,
    "source_category": "search",
    "query": "מטבוחה",
    "tier": "mainstream",
    "suggested_decision": "YES",
    "decision_reason": "positive_type:מטבוחה",
    "approved_for_scrape": "NO"
  },
  {
    "name": "סלט מטבוחה פיקנטי",
    "code": "P_7296073725510",
    "categories": "[A16, A1624, A162407, categories, A]",
    "price": "14.9",
    "weight_g": null,
    "source_category": "search",
    "query": "מטבוחה",
    "tier": "mainstream",
    "suggested_decision": "YES",
    "decision_reason": "positive_type:מטבוחה",
    "approved_for_scrape": "NO"
  },
  {
    "name": "מטבוחה אמיתית",
    "code": "P_7290106577572",
    "categories": "[A16, A1624, A162407, categories, A]",
    "price": "15.5",
    "weight_g": null,
    "source_category": "search",
    "query": "מטבוחה",
    "tier": "mainstream",
    "suggested_decision": "YES",
    "decision_reason": "positive_type:מטבוחה",
    "approved_for_scrape": "NO"
  },
  {
    "name": "סלט מטבוחה",
    "code": "P_6666444",
    "categories": "[A24, A16, A1624, A162407, categories, A, A2414]",
    "price": "22.9",
    "weight_g": null,
    "source_category": "search",
    "query": "מטבוחה",
    "tier": "mainstream",
    "suggested_decision": "YES",
    "decision_reason": "positive_type:מטבוחה",
    "approved_for_scrape": "NO"
  },
  {
    "name": "ממרח לימון באלדי",
    "code": "P_7296073749516",
    "categories": "[A16, A1624, A162405, categories, A]",
    "price": "14.5",
    "weight_g": null,
    "source_category": "search",
    "query": "ממרח חצילים",
    "tier": "mainstream",
    "suggested_decision": "REVIEW",
    "decision_reason": "possible_target",
    "approved_for_scrape": "NO"
  },
  {
    "name": "חציל",
    "code": "P_114",
    "categories": "[A04, A0410, categories, A041001, A]",
    "price": "9.9",
    "weight_g": null,
    "source_category": "search",
    "query": "ממרח חצילים",
    "tier": "mainstream",
    "suggested_decision": "REVIEW",
    "decision_reason": "needs_manual_check",
    "approved_for_scrape": "NO"
  },
  {
    "name": "חציל בלדי",
    "code": "P_962474",
    "categories": "[A04, A0410, categories, A041001, A]",
    "price": "9.9",
    "weight_g": null,
    "source_category": "search",
    "query": "ממרח חצילים",
    "tier": "mainstream",
    "suggested_decision": "REVIEW",
    "decision_reason": "needs_manual_check",
    "approved_for_scrape": "NO"
  },
  {
    "name": "מארז חציל אורגני",
    "code": "P_9136913",
    "categories": "[A04, categories, F01, A281704, F010202, A0411, F, A0410, A2817, A28, A041001, A, F0102, A041102]",
    "price": "16.9",
    "weight_g": null,
    "source_category": "search",
    "query": "ממרח חצילים",
    "tier": "mainstream",
    "suggested_decision": "REVIEW",
    "decision_reason": "needs_manual_check",
    "approved_for_scrape": "NO"
  },
  {
    "name": "מעדן חצילים",
    "code": "P_7296073725640",
    "categories": "[A16, A1624, A162407, categories, A]",
    "price": "12.9",
    "weight_g": null,
    "source_category": "search",
    "query": "ממרח חצילים",
    "tier": "mainstream",
    "suggested_decision": "REVIEW",
    "decision_reason": "needs_manual_check",
    "approved_for_scrape": "NO"
  },
  {
    "name": "סלט חצילים על האש",
    "code": "P_7296073725497",
    "categories": "[A16, A1624, A162407, categories, A]",
    "price": "14.9",
    "weight_g": null,
    "source_category": "search",
    "query": "ממרח חצילים",
    "tier": "mainstream",
    "suggested_decision": "REVIEW",
    "decision_reason": "needs_manual_check",
    "approved_for_scrape": "NO"
  },
  {
    "name": "ממרח פלפלים קלויים",
    "code": "P_6724786",
    "categories": "[A2805, F10, F, A280507, categories, A28, F1004, A, F100402]",
    "price": "20.9",
    "weight_g": null,
    "source_category": "search",
    "query": "ממרח פלפל",
    "tier": "specialty",
    "suggested_decision": "YES",
    "decision_reason": "positive_type:ממרח פלפל",
    "approved_for_scrape": "NO"
  },
  {
    "name": "פלפל מתוק ארוז",
    "code": "P_7296073417446",
    "categories": "[A04, A0410, categories, A041001, A]",
    "price": "14.9",
    "weight_g": null,
    "source_category": "search",
    "query": "ממרח פלפל",
    "tier": "specialty",
    "suggested_decision": "REVIEW",
    "decision_reason": "needs_manual_check",
    "approved_for_scrape": "NO"
  },
  {
    "name": "פלפל אדום",
    "code": "P_91",
    "categories": "[A04, A0410, categories, A041001, A]",
    "price": "12.9",
    "weight_g": null,
    "source_category": "search",
    "query": "ממרח פלפל",
    "tier": "specialty",
    "suggested_decision": "REVIEW",
    "decision_reason": "needs_manual_check",
    "approved_for_scrape": "NO"
  },
  {
    "name": "מארז פלפל פדרון",
    "code": "P_7290016809473",
    "categories": "[A04, A0410, categories, A041001, A]",
    "price": "12.9",
    "weight_g": null,
    "source_category": "search",
    "query": "ממרח פלפל",
    "tier": "specialty",
    "suggested_decision": "REVIEW",
    "decision_reason": "needs_manual_check",
    "approved_for_scrape": "NO"
  },
  {
    "name": "פלפל אדום ארוז",
    "code": "P_7296073440413",
    "categories": "[A04, A0410, categories, A041001, A]",
    "price": "12.9",
    "weight_g": null,
    "source_category": "search",
    "query": "ממרח פלפל",
    "tier": "specialty",
    "suggested_decision": "REVIEW",
    "decision_reason": "needs_manual_check",
    "approved_for_scrape": "NO"
  },
  {
    "name": "פלפל צהוב ארוז",
    "code": "P_7296073440499",
    "categories": "[A04, A0410, categories, A041001, A]",
    "price": "12.9",
    "weight_g": null,
    "source_category": "search",
    "query": "ממרח פלפל",
    "tier": "specialty",
    "suggested_decision": "REVIEW",
    "decision_reason": "needs_manual_check",
    "approved_for_scrape": "NO"
  },
  {
    "name": "פלפל צהוב",
    "code": "P_855",
    "categories": "[A04, A0410, categories, A041001, A]",
    "price": "12.9",
    "weight_g": null,
    "source_category": "search",
    "query": "ממרח פלפל",
    "tier": "specialty",
    "suggested_decision": "REVIEW",
    "decision_reason": "needs_manual_check",
    "approved_for_scrape": "NO"
  },
  {
    "name": "פלפל כתום",
    "code": "P_961552",
    "categories": "[A04, A0410, categories, A041001, A]",
    "price": "12.9",
    "weight_g": null,
    "source_category": "search",
    "query": "ממרח פלפל",
    "tier": "specialty",
    "suggested_decision": "REVIEW",
    "decision_reason": "needs_manual_check",
    "approved_for_scrape": "NO"
  },
  {
    "name": "מארז פלפל אדום אורגני",
    "code": "P_9137057",
    "categories": "[A04, categories, F01, A281704, F010202, A0411, F, A0410, A2817, A041001, A28, A, F0102, A041102]",
    "price": "22.9",
    "weight_g": null,
    "source_category": "search",
    "query": "ממרח פלפל",
    "tier": "specialty",
    "suggested_decision": "REVIEW",
    "decision_reason": "needs_manual_check",
    "approved_for_scrape": "NO"
  },
  {
    "name": "פלפל שישקה מתוק",
    "code": "P_749",
    "categories": "[A04, A0410, categories, A041001, A]",
    "price": "14.9",
    "weight_g": null,
    "source_category": "search",
    "query": "ממרח פלפל",
    "tier": "specialty",
    "suggested_decision": "REVIEW",
    "decision_reason": "needs_manual_check",
    "approved_for_scrape": "NO"
  },
  {
    "name": "מארז פלפלון",
    "code": "P_7290016334173",
    "categories": "[A04, A0410, categories, A041001, A]",
    "price": "9.9",
    "weight_g": null,
    "source_category": "search",
    "query": "ממרח פלפל",
    "tier": "specialty",
    "suggested_decision": "REVIEW",
    "decision_reason": "needs_manual_check",
    "approved_for_scrape": "NO"
  },
  {
    "name": "פלפל צ'ומה",
    "code": "P_7290010154265",
    "categories": "[A16, A1624, A162405, categories, A]",
    "price": "16.5",
    "weight_g": null,
    "source_category": "search",
    "query": "פלפל צ'ומה",
    "tier": "specialty",
    "suggested_decision": "YES",
    "decision_reason": "positive_type:פלפל צ'ומה",
    "approved_for_scrape": "NO"
  },
  {
    "name": "פלפל בהיר ארוז",
    "code": "P_7296073440482",
    "categories": "[A04, A0410, categories, A041001, A]",
    "price": "10.9",
    "weight_g": null,
    "source_category": "search",
    "query": "פלפל צ'ומה",
    "tier": "specialty",
    "suggested_decision": "REVIEW",
    "decision_reason": "needs_manual_check",
    "approved_for_scrape": "NO"
  },
  {
    "name": "פלפל מתוק יבש",
    "code": "P_7290016334487",
    "categories": "[A04, A0410, categories, A041001, A]",
    "price": "14.9",
    "weight_g": null,
    "source_category": "search",
    "query": "פלפל צ'ומה",
    "tier": "specialty",
    "suggested_decision": "REVIEW",
    "decision_reason": "needs_manual_check",
    "approved_for_scrape": "NO"
  },
  {
    "name": "פלפל פלרמו איטלקי מתוק",
    "code": "P_7290016809022",
    "categories": "[A04, A0410, categories, A041001, A]",
    "price": "11.9",
    "weight_g": null,
    "source_category": "search",
    "query": "פלפל צ'ומה",
    "tier": "specialty",
    "suggested_decision": "REVIEW",
    "decision_reason": "needs_manual_check",
    "approved_for_scrape": "NO"
  },
  {
    "name": "פלפל ירוק כהה",
    "code": "P_107",
    "categories": "[A04, A0410, categories, A041001, A]",
    "price": "10.9",
    "weight_g": null,
    "source_category": "search",
    "query": "פלפל צ'ומה",
    "tier": "specialty",
    "suggested_decision": "REVIEW",
    "decision_reason": "needs_manual_check",
    "approved_for_scrape": "NO"
  },
  {
    "name": "פלפל ירוק בהיר",
    "code": "P_84",
    "categories": "[A04, A0410, categories, A041001, A]",
    "price": "10.9",
    "weight_g": null,
    "source_category": "search",
    "query": "פלפל צ'ומה",
    "tier": "specialty",
    "suggested_decision": "REVIEW",
    "decision_reason": "needs_manual_check",
    "approved_for_scrape": "NO"
  },
  {
    "name": "סלט כרוב אדום אחלה",
    "code": "P_7290103404758",
    "categories": "[A16, A1624, A162407, A162404, A162406, categories, A]",
    "price": "5.0",
    "weight_g": null,
    "source_category": "search",
    "query": "אחלה חומוס",
    "tier": "brand",
    "suggested_decision": "REVIEW",
    "decision_reason": "needs_manual_check",
    "approved_for_scrape": "NO"
  },
  {
    "name": "חומוס עם חציל פיקנטי",
    "code": "P_7290119374885",
    "categories": "[A16, A1624, A162407, categories, A]",
    "price": "12.9",
    "weight_g": null,
    "source_category": "search",
    "query": "אחלה חומוס",
    "tier": "brand",
    "suggested_decision": "YES",
    "decision_reason": "positive_type:חומוס",
    "approved_for_scrape": "NO"
  },
  {
    "name": "טחינה יום יום",
    "code": "P_5174575",
    "categories": "[A16, A1624, A162407, A162406, categories, A]",
    "price": "5.0",
    "weight_g": null,
    "source_category": "search",
    "query": "אחלה חומוס",
    "tier": "brand",
    "suggested_decision": "REVIEW",
    "decision_reason": "needs_manual_check",
    "approved_for_scrape": "NO"
  },
  {
    "name": "סלט פלפלים קלויים",
    "code": "P_7290104721533",
    "categories": "[A16, A1624, A162407, categories, A]",
    "price": "16.5",
    "weight_g": null,
    "source_category": "search",
    "query": "אחלה חומוס",
    "tier": "brand",
    "suggested_decision": "REVIEW",
    "decision_reason": "needs_manual_check",
    "approved_for_scrape": "NO"
  },
  {
    "name": "חומוס אבו מרוואן26%טחינה",
    "code": "P_7290122780314",
    "categories": "[A16, A1624, A162406, categories, A]",
    "price": "10.9",
    "weight_g": null,
    "source_category": "search",
    "query": "צבר חומוס",
    "tier": "brand",
    "suggested_decision": "YES",
    "decision_reason": "positive_type:חומוס",
    "approved_for_scrape": "NO"
  },
  {
    "name": "סלט כרוב אדום",
    "code": "P_7290106577541",
    "categories": "[A24, A16, A2406, A1624, A162407, A162404, categories, A]",
    "price": "15.5",
    "weight_g": null,
    "source_category": "search",
    "query": "צבר חומוס",
    "tier": "brand",
    "suggested_decision": "REVIEW",
    "decision_reason": "needs_manual_check",
    "approved_for_scrape": "NO"
  },
  {
    "name": "חציל על האש",
    "code": "P_7290115207484",
    "categories": "[A16, A1624, A162407, categories, A]",
    "price": "18.5",
    "weight_g": null,
    "source_category": "search",
    "query": "צבר חומוס",
    "tier": "brand",
    "suggested_decision": "REVIEW",
    "decision_reason": "needs_manual_check",
    "approved_for_scrape": "NO"
  },
  {
    "name": "הקיסר חומוס ענק",
    "code": "P_7290018359686",
    "categories": "[A221707, A2217, A22, categories, A]",
    "price": "10.9",
    "weight_g": null,
    "source_category": "search",
    "query": "ידין חומוס",
    "tier": "brand",
    "suggested_decision": "YES",
    "decision_reason": "positive_type:חומוס",
    "approved_for_scrape": "NO"
  },
  {
    "name": "גרגירי חומוס",
    "code": "P_7290018989289",
    "categories": "[A24, A2406, A221707, A2217, A22, categories, A]",
    "price": "10.9",
    "weight_g": null,
    "source_category": "search",
    "query": "ידין חומוס",
    "tier": "brand",
    "suggested_decision": "YES",
    "decision_reason": "positive_type:חומוס",
    "approved_for_scrape": "NO"
  },
  {
    "name": "גרגירי חומוס שלמים",
    "code": "P_7290016087772",
    "categories": "[A221707, A2217, A22, categories, A]",
    "price": "9.9",
    "weight_g": null,
    "source_category": "search",
    "query": "ידין חומוס",
    "tier": "brand",
    "suggested_decision": "YES",
    "decision_reason": "positive_type:חומוס",
    "approved_for_scrape": "NO"
  },
  {
    "name": "גרגרי חומוס",
    "code": "P_7290112357113",
    "categories": "[A24, A2406, A221707, A2217, A22, categories, A]",
    "price": "8.9",
    "weight_g": null,
    "source_category": "search",
    "query": "ידין חומוס",
    "tier": "brand",
    "suggested_decision": "YES",
    "decision_reason": "positive_type:חומוס",
    "approved_for_scrape": "NO"
  },
  {
    "name": "גרגרי חומוס להכנה ביתית",
    "code": "P_7290017105895",
    "categories": "[A24, A2406, A221707, A2217, A22, categories, A]",
    "price": "10.0",
    "weight_g": null,
    "source_category": "search",
    "query": "ידין חומוס",
    "tier": "brand",
    "suggested_decision": "YES",
    "decision_reason": "positive_type:חומוס",
    "approved_for_scrape": "NO"
  },
  {
    "name": "גרגרי חומוס מבושל מוקפא",
    "code": "P_104805",
    "categories": "[A160501, A24, A16, A2406, categories, A, A1605]",
    "price": "21.5",
    "weight_g": null,
    "source_category": "search",
    "query": "ידין חומוס",
    "tier": "brand",
    "suggested_decision": "YES",
    "decision_reason": "positive_type:חומוס",
    "approved_for_scrape": "NO"
  },
  {
    "name": "גרגירי חומוס שלמים",
    "code": "P_7290016087901",
    "categories": "[A221707, A2217, A22, categories, A]",
    "price": "8.9",
    "weight_g": null,
    "source_category": "search",
    "query": "ידין חומוס",
    "tier": "brand",
    "suggested_decision": "YES",
    "decision_reason": "positive_type:חומוס",
    "approved_for_scrape": "NO"
  },
  {
    "name": "זרעי חומוס",
    "code": "P_7290107779395",
    "categories": "[A04, A0410, categories, A, A041003]",
    "price": "9.9",
    "weight_g": null,
    "source_category": "search",
    "query": "ידין חומוס",
    "tier": "brand",
    "suggested_decision": "YES",
    "decision_reason": "positive_type:חומוס",
    "approved_for_scrape": "NO"
  }
]